map_closures/map_closures.py
map_closures/__init__.py
map_closures/pipeline.py
map_closures/pybind/map_closures_pybind.cpython-39-x86_64-linux-gnu.so
map_closures/pybind/lib64/libopencv_imgproc.a
map_closures/pybind/lib64/libopencv_features2d.a
map_closures/pybind/lib64/libopencv_core.a
map_closures/pybind/lib64/opencv4/3rdparty/libippicv.a
map_closures/pybind/lib64/opencv4/3rdparty/libittnotify.a
map_closures/pybind/lib64/opencv4/3rdparty/liblibopenjp2.a
map_closures/pybind/lib64/opencv4/3rdparty/liblibjpeg-turbo.a
map_closures/pybind/lib64/opencv4/3rdparty/libippiw.a
map_closures/pybind/lib64/cmake/opencv4/OpenCVModules.cmake
map_closures/pybind/lib64/cmake/opencv4/OpenCVModules-release.cmake
map_closures/pybind/lib64/cmake/opencv4/OpenCVConfig-version.cmake
map_closures/pybind/lib64/cmake/opencv4/OpenCVConfig.cmake
map_closures/pybind/bin/setup_vars_opencv4.sh
map_closures/pybind/include/opencv4/opencv2/features2d.hpp
map_closures/pybind/include/opencv4/opencv2/cvconfig.h
map_closures/pybind/include/opencv4/opencv2/opencv.hpp
map_closures/pybind/include/opencv4/opencv2/opencv_modules.hpp
map_closures/pybind/include/opencv4/opencv2/imgproc.hpp
map_closures/pybind/include/opencv4/opencv2/core.hpp
map_closures/pybind/include/opencv4/opencv2/core/bindings_utils.hpp
map_closures/pybind/include/opencv4/opencv2/core/traits.hpp
map_closures/pybind/include/opencv4/opencv2/core/cv_cpu_helper.h
map_closures/pybind/include/opencv4/opencv2/core/check.hpp
map_closures/pybind/include/opencv4/opencv2/core/va_intel.hpp
map_closures/pybind/include/opencv4/opencv2/core/cuda_types.hpp
map_closures/pybind/include/opencv4/opencv2/core/cvstd.inl.hpp
map_closures/pybind/include/opencv4/opencv2/core/directx.hpp
map_closures/pybind/include/opencv4/opencv2/core/optim.hpp
map_closures/pybind/include/opencv4/opencv2/core/types.hpp
map_closures/pybind/include/opencv4/opencv2/core/cvstd.hpp
map_closures/pybind/include/opencv4/opencv2/core/eigen.hpp
map_closures-2.0.2.dist-info/WHEEL
map_closures-2.0.2.dist-info/entry_points.txt
map_closures-2.0.2.dist-info/METADATA
map_closures-2.0.2.dist-info/RECORD
map_closures-2.0.2.dist-info/licenses/LICENSE
